minimal_hatch_project/__about__.py
minimal_hatch_project/__init__.py
minimal_hatch_project-0.0.1.dist-info/METADATA
minimal_hatch_project-0.0.1.dist-info/WHEEL
minimal_hatch_project-0.0.1.dist-info/licenses/LICENSE.txt
minimal_hatch_project-0.0.1.dist-info/RECORD
